collections_cache/__init__.py
collections_cache/collections_cache.py
collections_cache-2025.3.3.dist-info/LICENSE
collections_cache-2025.3.3.dist-info/METADATA
collections_cache-2025.3.3.dist-info/WHEEL
collections_cache-2025.3.3.dist-info/RECORD
