Metadata-Version: 2.1
Name: collections-cache
Version: 2025.3.3
Summary: collections-cache is a Python package for managing data collections across multiple SQLite databases. It allows efficient storage, retrieval, and updating of key-value pairs, supporting various data types serialized with pickle. The package uses parallel processing for fast access and manipulation of large collections.
License: MIT
Author: Luiz-Trindade
Author-email: luiz.gabriel.m.trindade@gmail.com
Requires-Python: >=3.12,<4.0
Classifier: License :: OSI Approved :: MIT License
Classifier: Programming Language :: Python :: 3
Classifier: Programming Language :: Python :: 3.12
